README
setup.py
marketplace/__init__.py
marketplace/application.py
marketplace/application/__init__.py
marketplace/application/application.py
marketplace/application/objects/__init__.py
marketplace/application/objects/marketplace.py
marketplace/objects/__init__.py
marketplace/objects/marketplace.py
uforge_marketplace_python_sdk.egg-info/PKG-INFO
uforge_marketplace_python_sdk.egg-info/SOURCES.txt
uforge_marketplace_python_sdk.egg-info/dependency_links.txt
uforge_marketplace_python_sdk.egg-info/requires.txt
uforge_marketplace_python_sdk.egg-info/top_level.txt